{"Sta104": ["Sta66", "Sta12", "Sta161", "Sta21", "Sta133", "Sta22", "Sta138", "Sta41", "Sta30", "Sta154", "Sta150", "Sta160", "Sta64", "Sta89", "Sta80", "Sta97", "Sta110", "Sta106", "Sta34", "Sta128", "Sta92", "Sta74", "Sta149", "Sta49", "Sta65", "Sta104"], "Sta65": ["Sta66", "Sta12", "Sta161", "Sta21", "Sta133", "Sta22", "Sta138", "Sta41", "Sta30", "Sta154", "Sta150", "Sta160", "Sta64", "Sta89", "Sta80", "Sta97", "Sta110", "Sta106", "Sta34", "Sta128", "Sta92", "Sta74", "Sta149", "Sta49", "Sta65"], "Sta49": ["Sta66", "Sta12", "Sta161", "Sta21", "Sta133", "Sta22", "Sta138", "Sta41", "Sta30", "Sta154", "Sta150", "Sta160", "Sta64", "Sta89", "Sta80", "Sta97", "Sta110", "Sta106", "Sta34", "Sta128", "Sta92", "Sta74", "Sta149", "Sta49"], "Sta149": ["Sta66", "Sta12", "Sta161", "Sta21", "Sta133", "Sta22", "Sta138", "Sta41", "Sta30", "Sta154", "Sta150", "Sta160", "Sta64", "Sta89", "Sta80", "Sta97", "Sta110", "Sta106", "Sta34", "Sta128", "Sta92", "Sta74", "Sta149"], "Sta74": ["Sta66", "Sta12", "Sta161", "Sta21", "Sta133", "Sta22", "Sta138", "Sta41", "Sta30", "Sta154", "Sta150", "Sta160", "Sta64", "Sta89", "Sta80", "Sta97", "Sta110", "Sta106", "Sta34", "Sta128", "Sta92", "Sta74"], "Sta92": ["Sta66", "Sta12", "Sta161", "Sta21", "Sta133", "Sta22", "Sta138", "Sta41", "Sta30", "Sta154", "Sta150", "Sta160", "Sta64", "Sta89", "Sta80", "Sta97", "Sta110", "Sta106", "Sta34", "Sta128", "Sta92"], "Sta128": ["Sta66", "Sta12", "Sta161", "Sta21", "Sta133", "Sta22", "Sta138", "Sta41", "Sta30", "Sta154", "Sta150", "Sta160", "Sta64", "Sta89", "Sta80", "Sta97", "Sta110", "Sta106", "Sta34", "Sta128"], "Sta34": ["Sta66", "Sta12", "Sta161", "Sta21", "Sta133", "Sta22", "Sta138", "Sta41", "Sta30", "Sta154", "Sta150", "Sta160", "Sta64", "Sta89", "Sta80", "Sta97", "Sta110", "Sta106", "Sta34"], "Sta106": ["Sta66", "Sta12", "Sta161", "Sta21", "Sta133", "Sta22", "Sta138", "Sta41", "Sta30", "Sta154", "Sta150", "Sta160", "Sta64", "Sta89", "Sta80", "Sta97", "Sta110", "Sta106"], "Sta110": ["Sta66", "Sta12", "Sta161", "Sta21", "Sta133", "Sta22", "Sta138", "Sta41", "Sta30", "Sta154", "Sta150", "Sta160", "Sta64", "Sta89", "Sta80", "Sta97", "Sta110"], "Sta97": ["Sta66", "Sta12", "Sta161", "Sta21", "Sta133", "Sta22", "Sta138", "Sta41", "Sta30", "Sta154", "Sta150", "Sta160", "Sta64", "Sta89", "Sta80", "Sta97"], "Sta80": ["Sta66", "Sta12", "Sta161", "Sta21", "Sta133", "Sta22", "Sta138", "Sta41", "Sta30", "Sta154", "Sta150", "Sta160", "Sta64", "Sta89", "Sta80"], "Sta89": ["Sta66", "Sta12", "Sta161", "Sta21", "Sta133", "Sta22", "Sta138", "Sta41", "Sta30", "Sta154", "Sta150", "Sta160", "Sta64", "Sta89"], "Sta64": ["Sta66", "Sta12", "Sta161", "Sta21", "Sta133", "Sta22", "Sta138", "Sta41", "Sta30", "Sta154", "Sta150", "Sta160", "Sta64"], "Sta160": ["Sta66", "Sta12", "Sta161", "Sta21", "Sta133", "Sta22", "Sta138", "Sta41", "Sta30", "Sta154", "Sta150", "Sta160"], "Sta150": ["Sta66", "Sta12", "Sta161", "Sta21", "Sta133", "Sta22", "Sta138", "Sta41", "Sta30", "Sta154", "Sta150"], "Sta154": ["Sta66", "Sta12", "Sta161", "Sta21", "Sta133", "Sta22", "Sta138", "Sta41", "Sta30", "Sta154"], "Sta107": ["Sta66", "Sta12", "Sta161", "Sta21", "Sta133", "Sta22", "Sta138", "Sta41", "Sta30", "Sta154", "Sta107"], "Sta83": ["Sta66", "Sta12", "Sta161", "Sta21", "Sta133", "Sta22", "Sta138", "Sta41", "Sta30", "Sta154", "Sta107", "Sta83"], "Sta108": ["Sta66", "Sta12", "Sta161", "Sta21", "Sta133", "Sta22", "Sta138", "Sta41", "Sta30", "Sta154", "Sta107", "Sta83", "Sta108"], "Sta159": ["Sta66", "Sta12", "Sta161", "Sta21", "Sta133", "Sta22", "Sta138", "Sta41", "Sta30", "Sta154", "Sta107", "Sta83", "Sta108", "Sta159"], "Sta1": ["Sta66", "Sta12", "Sta161", "Sta21", "Sta133", "Sta22", "Sta138", "Sta41", "Sta30", "Sta154", "Sta107", "Sta83", "Sta108", "Sta159", "Sta1"], "Sta102": ["Sta66", "Sta12", "Sta161", "Sta21", "Sta133", "Sta22", "Sta138", "Sta41", "Sta30", "Sta154", "Sta150", "Sta160", "Sta7", "Sta6", "Sta8", "Sta75", "Sta102"], "Sta75": ["Sta66", "Sta12", "Sta161", "Sta21", "Sta133", "Sta22", "Sta138", "Sta41", "Sta30", "Sta154", "Sta150", "Sta160", "Sta7", "Sta6", "Sta8", "Sta75"], "Sta8": ["Sta66", "Sta12", "Sta161", "Sta21", "Sta133", "Sta22", "Sta138", "Sta41", "Sta30", "Sta154", "Sta150", "Sta160", "Sta7", "Sta6", "Sta8"], "Sta6": ["Sta66", "Sta12", "Sta161", "Sta21", "Sta133", "Sta22", "Sta138", "Sta41", "Sta30", "Sta154", "Sta150", "Sta160", "Sta7", "Sta6"], "Sta7": ["Sta66", "Sta12", "Sta161", "Sta21", "Sta133", "Sta22", "Sta138", "Sta41", "Sta30", "Sta154", "Sta150", "Sta160", "Sta7"], "Sta94": ["Sta66", "Sta12", "Sta161", "Sta21", "Sta133", "Sta22", "Sta138", "Sta41", "Sta30", "Sta154", "Sta150", "Sta160", "Sta94"], "Sta87": ["Sta66", "Sta12", "Sta161", "Sta21", "Sta133", "Sta22", "Sta138", "Sta41", "Sta30", "Sta154", "Sta150", "Sta160", "Sta94", "Sta87"], "Sta162": ["Sta66", "Sta12", "Sta161", "Sta21", "Sta133", "Sta22", "Sta138", "Sta41", "Sta30", "Sta154", "Sta150", "Sta160", "Sta94", "Sta87", "Sta162"], "Sta88": ["Sta66", "Sta12", "Sta161", "Sta21", "Sta133", "Sta22", "Sta138", "Sta41", "Sta30", "Sta154", "Sta150", "Sta160", "Sta94", "Sta87", "Sta162", "Sta88"], "Sta145": ["Sta66", "Sta12", "Sta161", "Sta21", "Sta133", "Sta22", "Sta138", "Sta41", "Sta30", "Sta154", "Sta150", "Sta160", "Sta94", "Sta87", "Sta162", "Sta88", "Sta145"], "Sta103": ["Sta66", "Sta12", "Sta161", "Sta21", "Sta133", "Sta22", "Sta138", "Sta41", "Sta30", "Sta154", "Sta150", "Sta160", "Sta94", "Sta87", "Sta162", "Sta88", "Sta145", "Sta103"], "Sta4": ["Sta66", "Sta12", "Sta161", "Sta21", "Sta133", "Sta22", "Sta138", "Sta41", "Sta30", "Sta154", "Sta150", "Sta160", "Sta94", "Sta87", "Sta162", "Sta88", "Sta145", "Sta103", "Sta4"], "Sta2": ["Sta66", "Sta12", "Sta161", "Sta21", "Sta133", "Sta22", "Sta138", "Sta41", "Sta30", "Sta154", "Sta150", "Sta160", "Sta94", "Sta87", "Sta162", "Sta88", "Sta145", "Sta103", "Sta4", "Sta2"], "Sta100": ["Sta66", "Sta12", "Sta161", "Sta21", "Sta133", "Sta22", "Sta138", "Sta41", "Sta30", "Sta154", "Sta150", "Sta160", "Sta94", "Sta87", "Sta162", "Sta88", "Sta145", "Sta103", "Sta4", "Sta2", "Sta100"], "Sta85": ["Sta66", "Sta12", "Sta161", "Sta21", "Sta133", "Sta22", "Sta138", "Sta41", "Sta30", "Sta154", "Sta150", "Sta160", "Sta94", "Sta87", "Sta162", "Sta88", "Sta145", "Sta103", "Sta4", "Sta2", "Sta100", "Sta85"], "Sta134": ["Sta66", "Sta12", "Sta161", "Sta21", "Sta133", "Sta22", "Sta138", "Sta41", "Sta30", "Sta154", "Sta150", "Sta160", "Sta94", "Sta87", "Sta162", "Sta88", "Sta145", "Sta103", "Sta4", "Sta2", "Sta100", "Sta85", "Sta134"], "Sta135": ["Sta66", "Sta12", "Sta161", "Sta21", "Sta133", "Sta22", "Sta138", "Sta41", "Sta30", "Sta154", "Sta150", "Sta160", "Sta94", "Sta87", "Sta162", "Sta88", "Sta145", "Sta103", "Sta4", "Sta2", "Sta100", "Sta85", "Sta134", "Sta135"], "Sta168": ["Sta66", "Sta12", "Sta161", "Sta21", "Sta133", "Sta22", "Sta138", "Sta41", "Sta30", "Sta154", "Sta150", "Sta160", "Sta94", "Sta87", "Sta162", "Sta88", "Sta145", "Sta103", "Sta4", "Sta2", "Sta100", "Sta85", "Sta134", "Sta135", "Sta168"], "Sta114": ["Sta66", "Sta12", "Sta161", "Sta21", "Sta133", "Sta22", "Sta138", "Sta41", "Sta30", "Sta154", "Sta150", "Sta160", "Sta94", "Sta87", "Sta162", "Sta88", "Sta145", "Sta103", "Sta4", "Sta2", "Sta100", "Sta85", "Sta134", "Sta135", "Sta168", "Sta114"], "Sta157": ["Sta66", "Sta12", "Sta161", "Sta21", "Sta133", "Sta22", "Sta138", "Sta41", "Sta30", "Sta154", "Sta150", "Sta160", "Sta94", "Sta87", "Sta162", "Sta88", "Sta145", "Sta103", "Sta4", "Sta2", "Sta100", "Sta85", "Sta134", "Sta135", "Sta168", "Sta114", "Sta157"], "Sta14": ["Sta66", "Sta12", "Sta161", "Sta21", "Sta133", "Sta22", "Sta138", "Sta41", "Sta30", "Sta154", "Sta150", "Sta160", "Sta64", "Sta89", "Sta80", "Sta97", "Sta110", "Sta106", "Sta34", "Sta128", "Sta92", "Sta116", "Sta32", "Sta91", "Sta60", "Sta148", "Sta73", "Sta14"], "Sta73": ["Sta66", "Sta12", "Sta161", "Sta21", "Sta133", "Sta22", "Sta138", "Sta41", "Sta30", "Sta154", "Sta150", "Sta160", "Sta64", "Sta89", "Sta80", "Sta97", "Sta110", "Sta106", "Sta34", "Sta128", "Sta92", "Sta116", "Sta32", "Sta91", "Sta60", "Sta148", "Sta73"], "Sta148": ["Sta66", "Sta12", "Sta161", "Sta21", "Sta133", "Sta22", "Sta138", "Sta41", "Sta30", "Sta154", "Sta150", "Sta160", "Sta64", "Sta89", "Sta80", "Sta97", "Sta110", "Sta106", "Sta34", "Sta128", "Sta92", "Sta116", "Sta32", "Sta91", "Sta60", "Sta148"], "Sta60": ["Sta66", "Sta12", "Sta161", "Sta21", "Sta133", "Sta22", "Sta138", "Sta41", "Sta30", "Sta154", "Sta150", "Sta160", "Sta64", "Sta89", "Sta80", "Sta97", "Sta110", "Sta106", "Sta34", "Sta128", "Sta92", "Sta116", "Sta32", "Sta91", "Sta60"], "Sta91": ["Sta66", "Sta12", "Sta161", "Sta21", "Sta133", "Sta22", "Sta138", "Sta41", "Sta30", "Sta154", "Sta150", "Sta160", "Sta64", "Sta89", "Sta80", "Sta97", "Sta110", "Sta106", "Sta34", "Sta128", "Sta92", "Sta116", "Sta32", "Sta91"], "Sta32": ["Sta66", "Sta12", "Sta161", "Sta21", "Sta133", "Sta22", "Sta138", "Sta41", "Sta30", "Sta154", "Sta150", "Sta160", "Sta64", "Sta89", "Sta80", "Sta97", "Sta110", "Sta106", "Sta34", "Sta128", "Sta92", "Sta116", "Sta32"], "Sta116": ["Sta66", "Sta12", "Sta161", "Sta21", "Sta133", "Sta22", "Sta138", "Sta41", "Sta30", "Sta154", "Sta150", "Sta160", "Sta64", "Sta89", "Sta80", "Sta97", "Sta110", "Sta106", "Sta34", "Sta128", "Sta92", "Sta116"], "Sta31": ["Sta66", "Sta12", "Sta161", "Sta21", "Sta133", "Sta22", "Sta138", "Sta41", "Sta30", "Sta154", "Sta150", "Sta160", "Sta64", "Sta89", "Sta80", "Sta97", "Sta110", "Sta106", "Sta34", "Sta128", "Sta92", "Sta31"], "Sta93": ["Sta66", "Sta12", "Sta161", "Sta21", "Sta133", "Sta22", "Sta138", "Sta41", "Sta30", "Sta154", "Sta150", "Sta160", "Sta64", "Sta89", "Sta80", "Sta97", "Sta110", "Sta106", "Sta34", "Sta128", "Sta92", "Sta31", "Sta93"], "Sta72": ["Sta66", "Sta12", "Sta161", "Sta21", "Sta133", "Sta22", "Sta138", "Sta41", "Sta30", "Sta154", "Sta150", "Sta160", "Sta64", "Sta89", "Sta80", "Sta97", "Sta110", "Sta106", "Sta34", "Sta128", "Sta92", "Sta31", "Sta93", "Sta72"], "Sta95": ["Sta66", "Sta12", "Sta161", "Sta21", "Sta133", "Sta22", "Sta138", "Sta41", "Sta30", "Sta154", "Sta150", "Sta160", "Sta64", "Sta89", "Sta80", "Sta97", "Sta110", "Sta106", "Sta34", "Sta128", "Sta92", "Sta31", "Sta93", "Sta72", "Sta95"], "Sta90": ["Sta66", "Sta12", "Sta161", "Sta21", "Sta133", "Sta22", "Sta138", "Sta41", "Sta30", "Sta154", "Sta150", "Sta160", "Sta64", "Sta89", "Sta80", "Sta97", "Sta110", "Sta106", "Sta34", "Sta128", "Sta92", "Sta31", "Sta93", "Sta72", "Sta95", "Sta90"], "Sta26": ["Sta66", "Sta12", "Sta161", "Sta21", "Sta133", "Sta22", "Sta138", "Sta41", "Sta30", "Sta154", "Sta150", "Sta160", "Sta64", "Sta89", "Sta80", "Sta97", "Sta110", "Sta106", "Sta34", "Sta128", "Sta92", "Sta31", "Sta93", "Sta72", "Sta95", "Sta90", "Sta26"], "Sta17": ["Sta66", "Sta12", "Sta161", "Sta21", "Sta133", "Sta22", "Sta138", "Sta41", "Sta30", "Sta154", "Sta150", "Sta160", "Sta94", "Sta87", "Sta162", "Sta115", "Sta118", "Sta56", "Sta23", "Sta20", "Sta55", "Sta70", "Sta13", "Sta111", "Sta140", "Sta101", "Sta17"], "Sta101": ["Sta66", "Sta12", "Sta161", "Sta21", "Sta133", "Sta22", "Sta138", "Sta41", "Sta30", "Sta154", "Sta150", "Sta160", "Sta94", "Sta87", "Sta162", "Sta115", "Sta118", "Sta56", "Sta23", "Sta20", "Sta55", "Sta70", "Sta13", "Sta111", "Sta140", "Sta101"], "Sta136": ["Sta66", "Sta12", "Sta161", "Sta21", "Sta133", "Sta22", "Sta138", "Sta41", "Sta30", "Sta154", "Sta150", "Sta160", "Sta94", "Sta87", "Sta162", "Sta115", "Sta118", "Sta56", "Sta23", "Sta20", "Sta55", "Sta70", "Sta13", "Sta111", "Sta140", "Sta101", "Sta136"], "Sta137": ["Sta66", "Sta12", "Sta161", "Sta21", "Sta133", "Sta22", "Sta138", "Sta41", "Sta30", "Sta154", "Sta150", "Sta160", "Sta94", "Sta87", "Sta162", "Sta115", "Sta118", "Sta56", "Sta23", "Sta20", "Sta55", "Sta70", "Sta13", "Sta111", "Sta140", "Sta101", "Sta136", "Sta137"], "Sta28": ["Sta66", "Sta12", "Sta161", "Sta21", "Sta133", "Sta22", "Sta138", "Sta41", "Sta30", "Sta154", "Sta150", "Sta160", "Sta94", "Sta87", "Sta162", "Sta115", "Sta118", "Sta56", "Sta23", "Sta20", "Sta55", "Sta70", "Sta13", "Sta111", "Sta140", "Sta101", "Sta77", "Sta122", "Sta36", "Sta166", "Sta99", "Sta124", "Sta28"], "Sta124": ["Sta66", "Sta12", "Sta161", "Sta21", "Sta133", "Sta22", "Sta138", "Sta41", "Sta30", "Sta154", "Sta150", "Sta160", "Sta94", "Sta87", "Sta162", "Sta115", "Sta118", "Sta56", "Sta23", "Sta20", "Sta55", "Sta70", "Sta13", "Sta111", "Sta140", "Sta101", "Sta77", "Sta122", "Sta36", "Sta166", "Sta99", "Sta124"], "Sta99": ["Sta66", "Sta12", "Sta161", "Sta21", "Sta133", "Sta22", "Sta138", "Sta41", "Sta30", "Sta154", "Sta150", "Sta160", "Sta94", "Sta87", "Sta162", "Sta115", "Sta118", "Sta56", "Sta23", "Sta20", "Sta55", "Sta70", "Sta13", "Sta111", "Sta140", "Sta101", "Sta77", "Sta122", "Sta36", "Sta166", "Sta99"], "Sta166": ["Sta66", "Sta12", "Sta161", "Sta21", "Sta133", "Sta22", "Sta138", "Sta41", "Sta30", "Sta154", "Sta150", "Sta160", "Sta94", "Sta87", "Sta162", "Sta115", "Sta118", "Sta56", "Sta23", "Sta20", "Sta55", "Sta70", "Sta13", "Sta111", "Sta140", "Sta101", "Sta77", "Sta122", "Sta36", "Sta166"], "Sta36": ["Sta66", "Sta12", "Sta161", "Sta21", "Sta133", "Sta22", "Sta138", "Sta41", "Sta30", "Sta154", "Sta150", "Sta160", "Sta94", "Sta87", "Sta162", "Sta115", "Sta118", "Sta56", "Sta23", "Sta20", "Sta55", "Sta70", "Sta13", "Sta111", "Sta140", "Sta101", "Sta77", "Sta122", "Sta36"], "Sta122": ["Sta66", "Sta12", "Sta161", "Sta21", "Sta133", "Sta22", "Sta138", "Sta41", "Sta30", "Sta154", "Sta150", "Sta160", "Sta94", "Sta87", "Sta162", "Sta115", "Sta118", "Sta56", "Sta23", "Sta20", "Sta55", "Sta70", "Sta13", "Sta111", "Sta140", "Sta101", "Sta77", "Sta122"], "Sta77": ["Sta66", "Sta12", "Sta161", "Sta21", "Sta133", "Sta22", "Sta138", "Sta41", "Sta30", "Sta154", "Sta150", "Sta160", "Sta94", "Sta87", "Sta162", "Sta115", "Sta118", "Sta56", "Sta23", "Sta20", "Sta55", "Sta70", "Sta13", "Sta111", "Sta140", "Sta101", "Sta77"], "Sta140": ["Sta66", "Sta12", "Sta161", "Sta21", "Sta133", "Sta22", "Sta138", "Sta41", "Sta30", "Sta154", "Sta150", "Sta160", "Sta94", "Sta87", "Sta162", "Sta115", "Sta118", "Sta56", "Sta23", "Sta20", "Sta55", "Sta70", "Sta13", "Sta111", "Sta140"], "Sta111": ["Sta66", "Sta12", "Sta161", "Sta21", "Sta133", "Sta22", "Sta138", "Sta41", "Sta30", "Sta154", "Sta150", "Sta160", "Sta94", "Sta87", "Sta162", "Sta115", "Sta118", "Sta56", "Sta23", "Sta20", "Sta55", "Sta70", "Sta13", "Sta111"], "Sta13": ["Sta66", "Sta12", "Sta161", "Sta21", "Sta133", "Sta22", "Sta138", "Sta41", "Sta30", "Sta154", "Sta150", "Sta160", "Sta94", "Sta87", "Sta162", "Sta115", "Sta118", "Sta56", "Sta23", "Sta20", "Sta55", "Sta70", "Sta13"], "Sta70": ["Sta66", "Sta12", "Sta161", "Sta21", "Sta133", "Sta22", "Sta138", "Sta41", "Sta30", "Sta154", "Sta150", "Sta160", "Sta94", "Sta87", "Sta162", "Sta115", "Sta118", "Sta56", "Sta23", "Sta20", "Sta55", "Sta70"], "Sta55": ["Sta66", "Sta12", "Sta161", "Sta21", "Sta133", "Sta22", "Sta138", "Sta41", "Sta30", "Sta154", "Sta150", "Sta160", "Sta94", "Sta87", "Sta162", "Sta115", "Sta118", "Sta56", "Sta23", "Sta20", "Sta55"], "Sta20": ["Sta66", "Sta12", "Sta161", "Sta21", "Sta133", "Sta22", "Sta138", "Sta41", "Sta30", "Sta154", "Sta150", "Sta160", "Sta94", "Sta87", "Sta162", "Sta115", "Sta118", "Sta56", "Sta23", "Sta20"], "Sta23": ["Sta66", "Sta12", "Sta161", "Sta21", "Sta133", "Sta22", "Sta138", "Sta41", "Sta30", "Sta154", "Sta150", "Sta160", "Sta94", "Sta87", "Sta162", "Sta115", "Sta118", "Sta56", "Sta23"], "Sta56": ["Sta66", "Sta12", "Sta161", "Sta21", "Sta133", "Sta22", "Sta138", "Sta41", "Sta30", "Sta154", "Sta150", "Sta160", "Sta94", "Sta87", "Sta162", "Sta115", "Sta118", "Sta56"], "Sta118": ["Sta66", "Sta12", "Sta161", "Sta21", "Sta133", "Sta22", "Sta138", "Sta41", "Sta30", "Sta154", "Sta150", "Sta160", "Sta94", "Sta87", "Sta162", "Sta115", "Sta118"], "Sta115": ["Sta66", "Sta12", "Sta161", "Sta21", "Sta133", "Sta22", "Sta138", "Sta41", "Sta30", "Sta154", "Sta150", "Sta160", "Sta94", "Sta87", "Sta162", "Sta115"], "Sta15": ["Sta66", "Sta12", "Sta161", "Sta21", "Sta133", "Sta22", "Sta138", "Sta41", "Sta30", "Sta154", "Sta150", "Sta160", "Sta94", "Sta87", "Sta162", "Sta15"], "Sta86": ["Sta66", "Sta12", "Sta161", "Sta21", "Sta133", "Sta22", "Sta138", "Sta41", "Sta30", "Sta154", "Sta150", "Sta160", "Sta94", "Sta87", "Sta162", "Sta15", "Sta86"], "Sta46": ["Sta66", "Sta12", "Sta161", "Sta21", "Sta133", "Sta22", "Sta138", "Sta41", "Sta30", "Sta154", "Sta150", "Sta160", "Sta94", "Sta87", "Sta162", "Sta15", "Sta86", "Sta46"], "Sta63": ["Sta66", "Sta12", "Sta161", "Sta21", "Sta133", "Sta22", "Sta138", "Sta41", "Sta30", "Sta154", "Sta150", "Sta160", "Sta94", "Sta87", "Sta162", "Sta15", "Sta86", "Sta46", "Sta63"], "Sta3": ["Sta66", "Sta12", "Sta161", "Sta21", "Sta133", "Sta22", "Sta138", "Sta41", "Sta30", "Sta154", "Sta150", "Sta160", "Sta94", "Sta87", "Sta162", "Sta15", "Sta86", "Sta46", "Sta63", "Sta3"], "Sta25": ["Sta66", "Sta12", "Sta161", "Sta21", "Sta133", "Sta22", "Sta138", "Sta41", "Sta30", "Sta154", "Sta150", "Sta160", "Sta94", "Sta87", "Sta162", "Sta15", "Sta86", "Sta46", "Sta63", "Sta3", "Sta25"], "Sta146": ["Sta66", "Sta12", "Sta161", "Sta21", "Sta133", "Sta22", "Sta138", "Sta41", "Sta30", "Sta154", "Sta150", "Sta160", "Sta94", "Sta87", "Sta162", "Sta15", "Sta86", "Sta46", "Sta63", "Sta3", "Sta25", "Sta146"], "Sta130": ["Sta66", "Sta12", "Sta161", "Sta21", "Sta133", "Sta22", "Sta138", "Sta41", "Sta30", "Sta154", "Sta150", "Sta160", "Sta94", "Sta87", "Sta162", "Sta15", "Sta86", "Sta46", "Sta63", "Sta3", "Sta25", "Sta146", "Sta130"], "Sta120": ["Sta66", "Sta12", "Sta161", "Sta21", "Sta133", "Sta22", "Sta138", "Sta41", "Sta30", "Sta154", "Sta150", "Sta160", "Sta94", "Sta87", "Sta162", "Sta15", "Sta86", "Sta46", "Sta63", "Sta3", "Sta25", "Sta146", "Sta130", "Sta120"], "Sta82": ["Sta66", "Sta12", "Sta161", "Sta21", "Sta133", "Sta22", "Sta138", "Sta41", "Sta30", "Sta154", "Sta150", "Sta160", "Sta94", "Sta87", "Sta162", "Sta15", "Sta86", "Sta46", "Sta63", "Sta3", "Sta25", "Sta146", "Sta130", "Sta120", "Sta82"], "Sta164": ["Sta66", "Sta12", "Sta161", "Sta21", "Sta133", "Sta22", "Sta138", "Sta41", "Sta30", "Sta154", "Sta150", "Sta160", "Sta94", "Sta87", "Sta162", "Sta15", "Sta86", "Sta46", "Sta63", "Sta3", "Sta25", "Sta146", "Sta130", "Sta120", "Sta82", "Sta164"], "Sta152": ["Sta66", "Sta12", "Sta161", "Sta21", "Sta133", "Sta22", "Sta138", "Sta41", "Sta30", "Sta154", "Sta150", "Sta160", "Sta94", "Sta87", "Sta162", "Sta15", "Sta86", "Sta46", "Sta63", "Sta3", "Sta25", "Sta146", "Sta130", "Sta120", "Sta82", "Sta164", "Sta152"], "Sta45": ["Sta66", "Sta12", "Sta161", "Sta21", "Sta133", "Sta22", "Sta138", "Sta41", "Sta30", "Sta154", "Sta150", "Sta160", "Sta94", "Sta87", "Sta162", "Sta15", "Sta86", "Sta46", "Sta63", "Sta3", "Sta25", "Sta146", "Sta130", "Sta120", "Sta82", "Sta164", "Sta152", "Sta45"], "Sta43": ["Sta66", "Sta12", "Sta161", "Sta21", "Sta133", "Sta22", "Sta138", "Sta41", "Sta30", "Sta154", "Sta150", "Sta160", "Sta94", "Sta87", "Sta162", "Sta115", "Sta118", "Sta56", "Sta23", "Sta132", "Sta96", "Sta10", "Sta43"], "Sta10": ["Sta66", "Sta12", "Sta161", "Sta21", "Sta133", "Sta22", "Sta138", "Sta41", "Sta30", "Sta154", "Sta150", "Sta160", "Sta94", "Sta87", "Sta162", "Sta115", "Sta118", "Sta56", "Sta23", "Sta132", "Sta96", "Sta10"], "Sta96": ["Sta66", "Sta12", "Sta161", "Sta21", "Sta133", "Sta22", "Sta138", "Sta41", "Sta30", "Sta154", "Sta150", "Sta160", "Sta94", "Sta87", "Sta162", "Sta115", "Sta118", "Sta56", "Sta23", "Sta132", "Sta96"], "Sta132": ["Sta66", "Sta12", "Sta161", "Sta21", "Sta133", "Sta22", "Sta138", "Sta41", "Sta30", "Sta154", "Sta150", "Sta160", "Sta94", "Sta87", "Sta162", "Sta115", "Sta118", "Sta56", "Sta23", "Sta132"], "Sta37": ["Sta66", "Sta12", "Sta161", "Sta21", "Sta133", "Sta22", "Sta138", "Sta41", "Sta30", "Sta154", "Sta150", "Sta160", "Sta64", "Sta89", "Sta80", "Sta97", "Sta16", "Sta37"], "Sta16": ["Sta66", "Sta12", "Sta161", "Sta21", "Sta133", "Sta22", "Sta138", "Sta41", "Sta30", "Sta154", "Sta150", "Sta160", "Sta64", "Sta89", "Sta80", "Sta97", "Sta16"], "Sta69": ["Sta66", "Sta12", "Sta161", "Sta21", "Sta133", "Sta22", "Sta138", "Sta41", "Sta30", "Sta154", "Sta150", "Sta160", "Sta64", "Sta89", "Sta80", "Sta97", "Sta69"], "Sta54": ["Sta66", "Sta12", "Sta161", "Sta21", "Sta133", "Sta22", "Sta138", "Sta41", "Sta30", "Sta154", "Sta150", "Sta160", "Sta64", "Sta89", "Sta80", "Sta97", "Sta69", "Sta54"], "Sta84": ["Sta66", "Sta12", "Sta161", "Sta21", "Sta133", "Sta22", "Sta138", "Sta41", "Sta30", "Sta154", "Sta150", "Sta160", "Sta94", "Sta87", "Sta162", "Sta88", "Sta145", "Sta126", "Sta40", "Sta131", "Sta84"], "Sta131": ["Sta66", "Sta12", "Sta161", "Sta21", "Sta133", "Sta22", "Sta138", "Sta41", "Sta30", "Sta154", "Sta150", "Sta160", "Sta94", "Sta87", "Sta162", "Sta88", "Sta145", "Sta126", "Sta40", "Sta131"], "Sta59": ["Sta66", "Sta12", "Sta161", "Sta21", "Sta133", "Sta22", "Sta138", "Sta41", "Sta30", "Sta154", "Sta150", "Sta160", "Sta94", "Sta87", "Sta162", "Sta88", "Sta145", "Sta126", "Sta40", "Sta131", "Sta59"], "Sta19": ["Sta66", "Sta12", "Sta161", "Sta21", "Sta133", "Sta22", "Sta138", "Sta41", "Sta30", "Sta154", "Sta150", "Sta160", "Sta94", "Sta87", "Sta162", "Sta88", "Sta145", "Sta126", "Sta40", "Sta131", "Sta59", "Sta19"], "Sta62": ["Sta66", "Sta12", "Sta161", "Sta21", "Sta133", "Sta22", "Sta138", "Sta41", "Sta30", "Sta154", "Sta150", "Sta160", "Sta94", "Sta87", "Sta162", "Sta88", "Sta145", "Sta126", "Sta40", "Sta131", "Sta59", "Sta19", "Sta62"], "Sta165": ["Sta66", "Sta12", "Sta161", "Sta21", "Sta133", "Sta22", "Sta138", "Sta41", "Sta30", "Sta154", "Sta150", "Sta160", "Sta94", "Sta87", "Sta162", "Sta88", "Sta145", "Sta126", "Sta40", "Sta131", "Sta59", "Sta19", "Sta62", "Sta165"], "Sta58": ["Sta66", "Sta12", "Sta161", "Sta21", "Sta133", "Sta22", "Sta138", "Sta41", "Sta30", "Sta154", "Sta150", "Sta160", "Sta94", "Sta87", "Sta162", "Sta88", "Sta145", "Sta126", "Sta40", "Sta131", "Sta59", "Sta19", "Sta62", "Sta165", "Sta58"], "Sta38": ["Sta66", "Sta12", "Sta161", "Sta21", "Sta133", "Sta22", "Sta138", "Sta41", "Sta30", "Sta154", "Sta150", "Sta160", "Sta94", "Sta87", "Sta162", "Sta88", "Sta145", "Sta126", "Sta40", "Sta131", "Sta59", "Sta19", "Sta62", "Sta165", "Sta58", "Sta38"], "Sta51": ["Sta66", "Sta12", "Sta161", "Sta21", "Sta133", "Sta22", "Sta138", "Sta41", "Sta30", "Sta154", "Sta150", "Sta160", "Sta64", "Sta89", "Sta27", "Sta48", "Sta151", "Sta68", "Sta52", "Sta76", "Sta57", "Sta71", "Sta139", "Sta24", "Sta105", "Sta51"], "Sta105": ["Sta66", "Sta12", "Sta161", "Sta21", "Sta133", "Sta22", "Sta138", "Sta41", "Sta30", "Sta154", "Sta150", "Sta160", "Sta64", "Sta89", "Sta27", "Sta48", "Sta151", "Sta68", "Sta52", "Sta76", "Sta57", "Sta71", "Sta139", "Sta24", "Sta105"], "Sta24": ["Sta66", "Sta12", "Sta161", "Sta21", "Sta133", "Sta22", "Sta138", "Sta41", "Sta30", "Sta154", "Sta150", "Sta160", "Sta64", "Sta89", "Sta27", "Sta48", "Sta151", "Sta68", "Sta52", "Sta76", "Sta57", "Sta71", "Sta139", "Sta24"], "Sta139": ["Sta66", "Sta12", "Sta161", "Sta21", "Sta133", "Sta22", "Sta138", "Sta41", "Sta30", "Sta154", "Sta150", "Sta160", "Sta64", "Sta89", "Sta27", "Sta48", "Sta151", "Sta68", "Sta52", "Sta76", "Sta57", "Sta71", "Sta139"], "Sta71": ["Sta66", "Sta12", "Sta161", "Sta21", "Sta133", "Sta22", "Sta138", "Sta41", "Sta30", "Sta154", "Sta150", "Sta160", "Sta64", "Sta89", "Sta27", "Sta48", "Sta151", "Sta68", "Sta52", "Sta76", "Sta57", "Sta71"], "Sta57": ["Sta66", "Sta12", "Sta161", "Sta21", "Sta133", "Sta22", "Sta138", "Sta41", "Sta30", "Sta154", "Sta150", "Sta160", "Sta64", "Sta89", "Sta27", "Sta48", "Sta151", "Sta68", "Sta52", "Sta76", "Sta57"], "Sta76": ["Sta66", "Sta12", "Sta161", "Sta21", "Sta133", "Sta22", "Sta138", "Sta41", "Sta30", "Sta154", "Sta150", "Sta160", "Sta64", "Sta89", "Sta27", "Sta48", "Sta151", "Sta68", "Sta52", "Sta76"], "Sta52": ["Sta66", "Sta12", "Sta161", "Sta21", "Sta133", "Sta22", "Sta138", "Sta41", "Sta30", "Sta154", "Sta150", "Sta160", "Sta64", "Sta89", "Sta27", "Sta48", "Sta151", "Sta68", "Sta52"], "Sta68": ["Sta66", "Sta12", "Sta161", "Sta21", "Sta133", "Sta22", "Sta138", "Sta41", "Sta30", "Sta154", "Sta150", "Sta160", "Sta64", "Sta89", "Sta27", "Sta48", "Sta151", "Sta68"], "Sta151": ["Sta66", "Sta12", "Sta161", "Sta21", "Sta133", "Sta22", "Sta138", "Sta41", "Sta30", "Sta154", "Sta150", "Sta160", "Sta64", "Sta89", "Sta27", "Sta48", "Sta151"], "Sta48": ["Sta66", "Sta12", "Sta161", "Sta21", "Sta133", "Sta22", "Sta138", "Sta41", "Sta30", "Sta154", "Sta150", "Sta160", "Sta64", "Sta89", "Sta27", "Sta48"], "Sta27": ["Sta66", "Sta12", "Sta161", "Sta21", "Sta133", "Sta22", "Sta138", "Sta41", "Sta30", "Sta154", "Sta150", "Sta160", "Sta64", "Sta89", "Sta27"], "Sta81": ["Sta66", "Sta12", "Sta161", "Sta21", "Sta133", "Sta22", "Sta138", "Sta41", "Sta30", "Sta154", "Sta150", "Sta160", "Sta64", "Sta89", "Sta81"], "Sta127": ["Sta66", "Sta12", "Sta161", "Sta21", "Sta133", "Sta22", "Sta138", "Sta41", "Sta30", "Sta154", "Sta67", "Sta47", "Sta123", "Sta127"], "Sta123": ["Sta66", "Sta12", "Sta161", "Sta21", "Sta133", "Sta22", "Sta138", "Sta41", "Sta30", "Sta154", "Sta67", "Sta47", "Sta123"], "Sta47": ["Sta66", "Sta12", "Sta161", "Sta21", "Sta133", "Sta22", "Sta138", "Sta41", "Sta30", "Sta154", "Sta67", "Sta47"], "Sta18": ["Sta66", "Sta12", "Sta161", "Sta21", "Sta133", "Sta22", "Sta138", "Sta41", "Sta30", "Sta154", "Sta67", "Sta47", "Sta18"], "Sta79": ["Sta66", "Sta12", "Sta161", "Sta21", "Sta133", "Sta22", "Sta138", "Sta41", "Sta30", "Sta154", "Sta67", "Sta47", "Sta18", "Sta79"], "Sta78": ["Sta66", "Sta12", "Sta161", "Sta21", "Sta133", "Sta22", "Sta138", "Sta41", "Sta30", "Sta154", "Sta67", "Sta47", "Sta18", "Sta79", "Sta78"], "Sta53": ["Sta66", "Sta12", "Sta161", "Sta21", "Sta133", "Sta22", "Sta138", "Sta41", "Sta30", "Sta154", "Sta67", "Sta47", "Sta18", "Sta79", "Sta78", "Sta53"], "Sta163": ["Sta66", "Sta12", "Sta161", "Sta21", "Sta133", "Sta22", "Sta138", "Sta41", "Sta30", "Sta154", "Sta107", "Sta83", "Sta108", "Sta129", "Sta9", "Sta163"], "Sta9": ["Sta66", "Sta12", "Sta161", "Sta21", "Sta133", "Sta22", "Sta138", "Sta41", "Sta30", "Sta154", "Sta107", "Sta83", "Sta108", "Sta129", "Sta9"], "Sta129": ["Sta66", "Sta12", "Sta161", "Sta21", "Sta133", "Sta22", "Sta138", "Sta41", "Sta30", "Sta154", "Sta107", "Sta83", "Sta108", "Sta129"], "Sta155": ["Sta66", "Sta119", "Sta50", "Sta61", "Sta156", "Sta143", "Sta155"], "Sta143": ["Sta66", "Sta119", "Sta50", "Sta61", "Sta156", "Sta143"], "Sta156": ["Sta66", "Sta119", "Sta50", "Sta61", "Sta156"], "Sta61": ["Sta66", "Sta119", "Sta50", "Sta61"], "Sta50": ["Sta66", "Sta119", "Sta50"], "Sta119": ["Sta66", "Sta119"], "Sta12": ["Sta66", "Sta12"], "Sta161": ["Sta66", "Sta12", "Sta161"], "Sta21": ["Sta66", "Sta12", "Sta161", "Sta21"], "Sta133": ["Sta66", "Sta12", "Sta161", "Sta21", "Sta133"], "Sta22": ["Sta66", "Sta12", "Sta161", "Sta21", "Sta133", "Sta22"], "Sta138": ["Sta66", "Sta12", "Sta161", "Sta21", "Sta133", "Sta22", "Sta138"], "Sta41": ["Sta66", "Sta12", "Sta161", "Sta21", "Sta133", "Sta22", "Sta138", "Sta41"], "Sta30": ["Sta66", "Sta12", "Sta161", "Sta21", "Sta133", "Sta22", "Sta138", "Sta41", "Sta30"], "Sta67": ["Sta66", "Sta12", "Sta161", "Sta21", "Sta133", "Sta22", "Sta138", "Sta41", "Sta30", "Sta154", "Sta67"], "Sta144": ["Sta66", "Sta12", "Sta161", "Sta21", "Sta133", "Sta22", "Sta138", "Sta41", "Sta30", "Sta154", "Sta67", "Sta47", "Sta144"], "Sta5": ["Sta66", "Sta12", "Sta161", "Sta21", "Sta133", "Sta22", "Sta138", "Sta41", "Sta30", "Sta154", "Sta67", "Sta47", "Sta144", "Sta5"], "Sta98": ["Sta66", "Sta12", "Sta161", "Sta21", "Sta133", "Sta22", "Sta138", "Sta41", "Sta30", "Sta154", "Sta67", "Sta47", "Sta144", "Sta5", "Sta98"], "Sta29": ["Sta66", "Sta12", "Sta161", "Sta21", "Sta133", "Sta22", "Sta138", "Sta41", "Sta30", "Sta154", "Sta150", "Sta160", "Sta94", "Sta87", "Sta162", "Sta15", "Sta29"], "Sta126": ["Sta66", "Sta12", "Sta161", "Sta21", "Sta133", "Sta22", "Sta138", "Sta41", "Sta30", "Sta154", "Sta150", "Sta160", "Sta94", "Sta87", "Sta162", "Sta88", "Sta145", "Sta126"], "Sta40": ["Sta66", "Sta12", "Sta161", "Sta21", "Sta133", "Sta22", "Sta138", "Sta41", "Sta30", "Sta154", "Sta150", "Sta160", "Sta94", "Sta87", "Sta162", "Sta88", "Sta145", "Sta126", "Sta40"], "Sta39": ["Sta66", "Sta12", "Sta161", "Sta21", "Sta133", "Sta22", "Sta138", "Sta41", "Sta30", "Sta154", "Sta150", "Sta160", "Sta94", "Sta87", "Sta162", "Sta88", "Sta145", "Sta126", "Sta40", "Sta131", "Sta39"], "Sta167": ["Sta66", "Sta12", "Sta161", "Sta21", "Sta133", "Sta22", "Sta138", "Sta41", "Sta30", "Sta154", "Sta150", "Sta160", "Sta94", "Sta87", "Sta162", "Sta88", "Sta145", "Sta103", "Sta4", "Sta2", "Sta100", "Sta167"], "Sta113": ["Sta66", "Sta12", "Sta161", "Sta21", "Sta133", "Sta22", "Sta138", "Sta41", "Sta30", "Sta154", "Sta150", "Sta160", "Sta94", "Sta87", "Sta162", "Sta88", "Sta145", "Sta103", "Sta4", "Sta2", "Sta100", "Sta167", "Sta113"], "Sta141": ["Sta66", "Sta12", "Sta161", "Sta21", "Sta133", "Sta22", "Sta138", "Sta41", "Sta30", "Sta154", "Sta150", "Sta160", "Sta94", "Sta87", "Sta162", "Sta88", "Sta145", "Sta103", "Sta4", "Sta2", "Sta100", "Sta167", "Sta113", "Sta141"], "Sta142": ["Sta66", "Sta12", "Sta161", "Sta21", "Sta133", "Sta22", "Sta138", "Sta41", "Sta30", "Sta154", "Sta150", "Sta160", "Sta94", "Sta87", "Sta162", "Sta88", "Sta145", "Sta103", "Sta4", "Sta2", "Sta100", "Sta167", "Sta113", "Sta141", "Sta142"], "Sta158": ["Sta66", "Sta12", "Sta161", "Sta21", "Sta133", "Sta22", "Sta138", "Sta41", "Sta30", "Sta154", "Sta150", "Sta160", "Sta94", "Sta87", "Sta162", "Sta88", "Sta145", "Sta103", "Sta4", "Sta2", "Sta100", "Sta167", "Sta113", "Sta141", "Sta142", "Sta158"], "Sta44": ["Sta66", "Sta12", "Sta161", "Sta21", "Sta133", "Sta22", "Sta138", "Sta41", "Sta30", "Sta154", "Sta150", "Sta160", "Sta94", "Sta87", "Sta162", "Sta88", "Sta145", "Sta103", "Sta4", "Sta2", "Sta100", "Sta167", "Sta113", "Sta141", "Sta142", "Sta158", "Sta44"], "Sta117": ["Sta66", "Sta12", "Sta161", "Sta21", "Sta133", "Sta22", "Sta138", "Sta41", "Sta30", "Sta154", "Sta150", "Sta160", "Sta94", "Sta87", "Sta162", "Sta88", "Sta145", "Sta103", "Sta4", "Sta2", "Sta100", "Sta167", "Sta113", "Sta141", "Sta142", "Sta158", "Sta44", "Sta117"], "Sta147": ["Sta66", "Sta12", "Sta161", "Sta21", "Sta133", "Sta22", "Sta138", "Sta41", "Sta30", "Sta154", "Sta150", "Sta160", "Sta94", "Sta87", "Sta162", "Sta88", "Sta145", "Sta103", "Sta4", "Sta2", "Sta100", "Sta167", "Sta113", "Sta141", "Sta142", "Sta158", "Sta44", "Sta117", "Sta147"], "Sta42": ["Sta66", "Sta12", "Sta161", "Sta21", "Sta133", "Sta22", "Sta138", "Sta41", "Sta30", "Sta154", "Sta150", "Sta160", "Sta94", "Sta87", "Sta162", "Sta88", "Sta145", "Sta103", "Sta4", "Sta2", "Sta100", "Sta167", "Sta113", "Sta141", "Sta142", "Sta158", "Sta44", "Sta117", "Sta147", "Sta42"], "Sta35": ["Sta66", "Sta12", "Sta161", "Sta21", "Sta133", "Sta22", "Sta138", "Sta41", "Sta30", "Sta154", "Sta150", "Sta160", "Sta94", "Sta87", "Sta162", "Sta88", "Sta145", "Sta103", "Sta4", "Sta2", "Sta100", "Sta167", "Sta113", "Sta141", "Sta142", "Sta158", "Sta44", "Sta117", "Sta147", "Sta42", "Sta35"], "Sta109": ["Sta66", "Sta12", "Sta161", "Sta21", "Sta133", "Sta22", "Sta138", "Sta41", "Sta30", "Sta154", "Sta150", "Sta160", "Sta94", "Sta87", "Sta162", "Sta88", "Sta145", "Sta103", "Sta4", "Sta2", "Sta100", "Sta167", "Sta113", "Sta141", "Sta142", "Sta158", "Sta44", "Sta117", "Sta147", "Sta42", "Sta35", "Sta109"], "Sta33": ["Sta66", "Sta12", "Sta161", "Sta21", "Sta133", "Sta22", "Sta138", "Sta41", "Sta30", "Sta154", "Sta150", "Sta160", "Sta94", "Sta87", "Sta162", "Sta88", "Sta145", "Sta103", "Sta4", "Sta2", "Sta100", "Sta167", "Sta113", "Sta141", "Sta142", "Sta158", "Sta44", "Sta117", "Sta147", "Sta42", "Sta35", "Sta109", "Sta33"], "Sta112": ["Sta66", "Sta12", "Sta161", "Sta21", "Sta133", "Sta22", "Sta138", "Sta41", "Sta30", "Sta154", "Sta150", "Sta160", "Sta94", "Sta87", "Sta162", "Sta88", "Sta145", "Sta103", "Sta4", "Sta2", "Sta100", "Sta167", "Sta113", "Sta141", "Sta142", "Sta158", "Sta44", "Sta117", "Sta147", "Sta42", "Sta35", "Sta109", "Sta33", "Sta112"], "Sta153": ["Sta66", "Sta12", "Sta161", "Sta21", "Sta133", "Sta22", "Sta138", "Sta41", "Sta30", "Sta154", "Sta150", "Sta160", "Sta94", "Sta87", "Sta162", "Sta88", "Sta145", "Sta103", "Sta4", "Sta2", "Sta100", "Sta167", "Sta113", "Sta141", "Sta142", "Sta158", "Sta44", "Sta117", "Sta147", "Sta42", "Sta35", "Sta109", "Sta33", "Sta112", "Sta153"], "Sta125": ["Sta66", "Sta12", "Sta161", "Sta21", "Sta133", "Sta22", "Sta138", "Sta41", "Sta30", "Sta154", "Sta150", "Sta160", "Sta94", "Sta87", "Sta162", "Sta88", "Sta145", "Sta103", "Sta4", "Sta2", "Sta100", "Sta167", "Sta113", "Sta141", "Sta142", "Sta158", "Sta44", "Sta117", "Sta147", "Sta42", "Sta35", "Sta109", "Sta33", "Sta112", "Sta153", "Sta125"], "Sta121": ["Sta66", "Sta12", "Sta161", "Sta21", "Sta133", "Sta22", "Sta138", "Sta41", "Sta30", "Sta154", "Sta150", "Sta160", "Sta94", "Sta87", "Sta162", "Sta88", "Sta145", "Sta103", "Sta4", "Sta2", "Sta100", "Sta167", "Sta113", "Sta141", "Sta142", "Sta158", "Sta44", "Sta117", "Sta147", "Sta42", "Sta35", "Sta109", "Sta33", "Sta112", "Sta153", "Sta125", "Sta121"], "Sta11": ["Sta66", "Sta12", "Sta161", "Sta21", "Sta133", "Sta22", "Sta138", "Sta41", "Sta30", "Sta154", "Sta150", "Sta160", "Sta94", "Sta87", "Sta162", "Sta88", "Sta145", "Sta103", "Sta4", "Sta2", "Sta100", "Sta167", "Sta113", "Sta141", "Sta142", "Sta158", "Sta44", "Sta117", "Sta147", "Sta42", "Sta35", "Sta109", "Sta33", "Sta112", "Sta153", "Sta125", "Sta121", "Sta11"]}